Dot_Plot/Dot_Plot.py
Dot_Plot/library/__init__.py
Dot_Plot/library/core.py
Dot_Plot/library/gui.py
Dot_Plot-0.1.2.1.dist-info/METADATA
Dot_Plot-0.1.2.1.dist-info/WHEEL
Dot_Plot-0.1.2.1.dist-info/top_level.txt
Dot_Plot-0.1.2.1.dist-info/RECORD
