Metadata-Version: 2.1
Name: Dot-Plot
Version: 0.1.2.1
Summary: Dot plot is a tool for creating svg images of chord and scale diagrams for fretboard instruments like guitar, bass, ukulele, viola da gamba etc
Home-page: UNKNOWN
Author: Nicola A. Cappellini
Author-email: nicola.cappellini@gmail.com
License: Private, non-commercial, no distribution
Platform: UNKNOWN
Requires-Python: >=3
Requires-Dist: drawSvg
